setup.py
gerritrestclient/__init__.py
gerritrestclient/accounts.py
gerritrestclient/changes.py
gerritrestclient/client.py
gerritrestclient/connection.py
gerritrestclient/endpoint.py
gerritrestclient/gerrit_entity.py
gerritrestclient/groups.py
gerritrestclient/projects.py
gerritrestclient.egg-info/PKG-INFO
gerritrestclient.egg-info/SOURCES.txt
gerritrestclient.egg-info/dependency_links.txt
gerritrestclient.egg-info/requires.txt
gerritrestclient.egg-info/top_level.txt