Metadata-Version: 1.0
Name: gerritrestclient
Version: 0.1
Summary: Client for Gerrit Code Review REST API
Home-page: http://github.com/lann/gerritrestclient
Author: Lann Martin
Author-email: gerritrestclient@lannbox.com
License: MIT
Platform: UNKNOWN
